analemma/__init__.py
analemma/geometry.py
analemma/orbit.py
analemma/plot.py
analemma/algebra/__init__.py
analemma/algebra/frame.py
analemma/algebra/render.py
analemma/algebra/result.py
analemma/algebra/util.py
analemma/tests/__init__.py
analemma/tests/conftest.py
analemma/tests/test_geometry.py
analemma/tests/test_orbit.py
analemma/tests/test_plot.py
analemma/tests/test_results.py
analemma-0.4.1.dist-info/licenses/LICENSE
analemma-0.4.1.dist-info/METADATA
analemma-0.4.1.dist-info/WHEEL
analemma-0.4.1.dist-info/top_level.txt
analemma-0.4.1.dist-info/RECORD
