Metadata-Version: 2.4
Name: analemma
Version: 0.4.1
Summary: Calculate sundial geometry and the equation of time, and plot the analemma
Author-email: Russell Goyder <russell.goyder@gmail.com>
License: MIT License
Project-URL: Homepage, https://russellgoyder.ca/analemma/
Project-URL: Documentation, https://analemma.readthedocs.io/en/stable/
Project-URL: Repository, https://github.com/russellgoyder/analemma
Project-URL: Issue Tracker, https://github.com/russellgoyder/analemma/issues
Project-URL: Changelog, https://analemma.readthedocs.io/en/stable/changelog/
Keywords: sundial,analemma,gnomon,equation of time,orbit
Classifier: Programming Language :: Python :: 3
Classifier: License :: OSI Approved :: MIT License
Classifier: Operating System :: OS Independent
Classifier: Intended Audience :: Science/Research
Classifier: Development Status :: 4 - Beta
License-File: LICENSE
Requires-Dist: numpy
Requires-Dist: scipy
Requires-Dist: skyfield
Requires-Dist: matplotlib
Requires-Dist: sympy
Requires-Dist: galgebra
Provides-Extra: dev
Requires-Dist: pytest>=8.3.4; extra == "dev"
Requires-Dist: ruff>=0.8.4; extra == "dev"
Dynamic: license-file
